Metadata-Version: 1.0
Name: Mahsanul-distributions
Version: 10.1
Summary: Gaussian distributions
Home-page: UNKNOWN
Author: UNKNOWN
Author-email: UNKNOWN
License: UNKNOWN
Platform: UNKNOWN
